<Properties StartupConfiguration="{D3BBB81E-9213-4201-BBD5-DCEAAAA8D3AB}|Default">
  <MonoDevelop.Ide.DebuggingService.PinnedWatches />
  <MonoDevelop.Ide.Workbench ActiveDocument="Object_Pool_Design_Pattern_Prac4/Program.cs">
    <Files>
      <File FileName="Object_Pool_Design_Pattern_Prac4/Program.cs" Line="21" Column="1" />
    </Files>
    <Pads>
      <Pad Id="ProjectPad">
        <State name="__root__">
          <Node name="Creational_Patterns">
            <Node name="Object_Pool_Design_Pattern_Prac4" expanded="True" />
          </Node>
        </State>
      </Pad>
    </Pads>
  </MonoDevelop.Ide.Workbench>
  <MonoDevelop.Ide.ItemProperties.Prototype__Design__Pattern PreferredExecutionTarget="MonoDevelop.Default" />
  <MonoDevelop.Ide.ItemProperties.Factory__Method__Design__Pattern__Prac2 PreferredExecutionTarget="MonoDevelop.Default" />
  <MonoDevelop.Ide.ItemProperties.Prototype__Design__Pattern__Prac2 PreferredExecutionTarget="MonoDevelop.Default" />
  <MonoDevelop.Ide.ItemProperties.Factory__Method__Design__Pattern PreferredExecutionTarget="MonoDevelop.Default" FirstBuild="True" />
  <MonoDevelop.Ide.ItemProperties.Abstract__Factory__Design__Pattern FirstBuild="True" />
  <MonoDevelop.Ide.ItemProperties.Object__Pool__Design__Pattern__Prac2 FirstBuild="True" />
  <MonoDevelop.Ide.ItemProperties.Singleton__Design__Pattern FirstBuild="True" />
  <MultiItemStartupConfigurations />
  <MonoDevelop.Ide.ItemProperties.Abstract__Factory__Design__Pattern__CSharp__Example FirstBuild="True" />
  <MonoDevelop.Ide.ItemProperties.Object__Pool__Design__Pattern__Prac3 PreferredExecutionTarget="MonoDevelop.Default" />
  <MonoDevelop.Ide.DebuggingService.Breakpoints>
    <Breakpoint file="/Users/dilanozer/Projects/Creational_Patterns/Object_Pool_Design_Pattern_Prac3/Program.cs" relfile="Object_Pool_Design_Pattern_Prac3/Program.cs" line="31" column="1" />
  </MonoDevelop.Ide.DebuggingService.Breakpoints>
  <MonoDevelop.Ide.Workspace ActiveConfiguration="Debug" />
  <MonoDevelop.Ide.ItemProperties.Factory__Design__Pattern FirstBuild="True" />
  <MonoDevelop.Ide.ItemProperties.Object__Pool__Design__Pattern PreferredExecutionTarget="MonoDevelop.Default" />
  <MonoDevelop.Ide.ItemProperties.Object__Pool__Design__Pattern__Prac4 PreferredExecutionTarget="MonoDevelop.Default" />
  <MonoDevelop.Ide.ItemProperties.Abstract__Factory__Design__Pattern__CSharp__Example__2 PreferredExecutionTarget="MonoDevelop.Default" />
  <MonoDevelop.Ide.ItemProperties.Object__Pool__Design__Pattern__CSharp__Example FirstBuild="True" />
</Properties>